mmoreira_csv_converter/__init__.py
mmoreira_csv_converter/csv2json.py
mmoreira_csv_converter-0.2.0.dist-info/entry_points.txt
mmoreira_csv_converter-0.2.0.dist-info/WHEEL
mmoreira_csv_converter-0.2.0.dist-info/METADATA
mmoreira_csv_converter-0.2.0.dist-info/RECORD
