Metadata-Version: 2.1
Name: mmoreira-csv-converter
Version: 0.2.0
Summary: Convert csv to json or convert json to csv. Publishing only for learning purpose at PUC-MG. DS Class
Author: Marcelo Moreira G Silva
Author-email: mqestatistico@gamil.com
Requires-Python: >=3.9,<4.0
Classifier: Programming Language :: Python :: 3
Classifier: Programming Language :: Python :: 3.10
Classifier: Programming Language :: Python :: 3.9
Requires-Dist: click (>=8.0.3,<9.0.0)
Requires-Dist: flake8 (>=4.0.1,<5.0.0)
